django_rocket/views.py
django_rocket/__init__.py
django_rocket/admin.py
django_rocket/models.py
django_rocket/utils.py
django_rocket/urls.py
django_rocket/signals.py
django_rocket/forms.py
django_rocket/middleware.py
django_rocket/templates/django_rocket/base.html
django_rocket/templates/django_rocket/request_access.html
django_rocket/templates/django_rocket/request_invitation_completed.html
django_rocket/templates/django_rocket/request_access_completed.html
django_rocket/templates/django_rocket/request_invitation.html
django_rocket/management/__init__.py
django_rocket/management/commands/invitation_token.py
django_rocket/management/commands/__init__.py
django_rocket/migrations/__init__.py
django_rocket/migrations/0001_initial.py
django_rocket-1.4.dist-info/METADATA
django_rocket-1.4.dist-info/DESCRIPTION.rst
django_rocket-1.4.dist-info/WHEEL
django_rocket-1.4.dist-info/RECORD
django_rocket-1.4.dist-info/metadata.json
django_rocket-1.4.dist-info/top_level.txt
