Metadata-Version: 2.0
Name: django-rocket
Version: 1.4
Summary: UNKNOWN
Home-page: https://github.com/mariocesar/django-rocket
Author: Mario César Señoranis Ayala
Author-email: mariocesar@creat1va.com
License: MIT
Download-URL: https://pypi.python.org/pypi/django-rocket
Platform: UNKNOWN
Classifier: Operating System :: OS Independent
Classifier: Intended Audience :: Developers
Classifier: License :: OSI Approved :: MIT License
Classifier: Programming Language :: Python
Classifier: Programming Language :: Python :: 2
Classifier: Programming Language :: Python :: 2.6
Classifier: Programming Language :: Python :: 2.7
Classifier: Programming Language :: Python :: 3
Classifier: Programming Language :: Python :: 3.2
Classifier: Programming Language :: Python :: 3.3
Classifier: Topic :: Internet :: WWW/HTTP :: Dynamic Content
Classifier: Development Status :: 5 - Production/Stable
Classifier: Environment :: Web Environment
Classifier: Framework :: Django
Requires-Dist: django (>1.5,<1.8)
Requires-Dist: wheel
Provides-Extra: develop
Requires-Dist: coverage; extra == 'develop'
Requires-Dist: sphinx; extra == 'develop'
Requires-Dist: sphinx-rtd-theme; extra == 'develop'
